[{"username":"test@gmail.com","password":"testpassword","firstname":"test","lastname":"","countchildren":2,"childrenname":["test1","test2"],"childrenage":["3","5"],"childrenallergy":["None","Mango"]},{"username":"mary@gmail.com","password":"maryhoute","firstname":"Mary","lastname":"Smith","countchildren":1,"childrenname":["Stella"],"childrenage":["4"],"childrenallergy":["None"]},{"username":"chad@gmail.com","password":"tatumchad","firstname":"Chad","lastname":"Tatum","countchildren":2,"childrenname":["Bella","Max"],"childrenage":["2","4"],"childrenallergy":["None","None"]},{"username":"maria@gmail.com","password":"Webb@123","firstname":"Maria","lastname":"Webb","countchildren":"2","childrenname":[["Stella","Max"],["","Ben"]],"childrenage":[["2","1"],["","4"]],"childrenallergy":[["None","Mango"],["","Honey"]]}]